Workbook

Sheet Income & Expenses
A3: Acct Name | C3: January | D3: February | E3: March | F3: April | G3: May | H3: June | I3: July | J3: August | K3: September | L3: October | M3: November | N3: December | P3: Total
A4: 2023 CARYOVER | C4: 5449.55
A5: Income | C5: 710.88 | D5: 954.22 | E5: 4938.48 | F5: 4432.97 | G5: 9530.77 | H5: 5804.68 | I5: 8905.06 | J5: 6041.71 | K5: 6803.08 | L5: 6020.03 | M5: 2123.95 | N5: 67.09 | P5: =SUM(C5:N5) -> 56332.92
P6: =SUM(C6:N6) -> 0
P7: =SUM(C7:N7) -> 0
P8: =SUM(C8:N8) -> 0
A9: Other source of funds: | P9: =SUM(C9:N9) -> 0
A10: Money from owner | P10: =SUM(C10:N10) -> 0
C11: =SUM(C4:C10) -> 6160.43 | D11: =SUM(D5:D10) -> 954.22 | E11: =SUM(E5:E10) -> 4938.48 | F11: =SUM(F5:F10) -> 4432.97 | G11: =SUM(G5:G10) -> 9530.77 | H11: =SUM(H5:H10) -> 5804.68 | I11: =SUM(I5:I10) -> 8905.06 | J11: =SUM(J5:J10) -> 6041.71 | K11: =SUM(K5:K10) -> 6803.08 | ... N11: =SUM(N5:N10) -> 67.09
A12: Acct Name | C12: January | D12: February | E12: March | F12: April | G12: May | H12: June | I12: July | J12: August | K12: September | L12: October | M12: November | N12: December | P12: Total
A14: Distributions to owner | P14: =SUM(C14:N14) -> 0
P15: =SUM(C15:N15) -> 0 | T15: 58.85
T16: 25
A17: Returns & Allowances | G17: 280.88 | I17: 83.85 | J17: 85 | K17: 89.61 | L17: 353.1 | M17: 48.15 | N17: 235.4 | P17: =SUM(C17:N17) -> 1175.99 | T17: =sum(T15:T16) -> 83.85
A19: Contract Labor | P19: =SUM(C19:N19) -> 0
A20: Andrew | C20: 260 | D20: 180 | E20: 1238 | F20: 1455 | G20: 2234 | H20: 2428 | I20: 2690 | J20: 1518 | K20: 2185 | L20: 1040 | P20: =SUM(C20:N20) -> 15228
A21: Justin | G21: 250 | L21: 200 | P21: =SUM(C21:N21) -> 450
A22: Nick | P22: =SUM(C22:N22) -> 0
A23: Ryan | L23: 250 | P23: =SUM(C23:N23) -> 250
A24: Ashton | H24: 475 | I24: 255 | L24: 165 | M24: 135 | P24: =SUM(C24:N24) -> 1030
A25: Savannah | P25: =SUM(C25:N25) -> 0
A26: Tires | P26: =SUM(C26:N26) -> 0
A27: Parts | P27: =SUM(C27:N27) -> 0
A28: Materials & Supplies | P28: =SUM(C28:N28) -> 0
A29: Fixed Asset Purchase | E29: 2000 | M29: 2375.59 | P29: =SUM(C29:N29) -> 4375.59 | Q29: enter add'l information for each purchase on separate tab
P30: =SUM(C30:N30) -> 0
A32: Accounting | P32: =SUM(C32:N32) -> 0
A33: Advertising | E33: 370 | F33: 58.23 | G33: 277.75 | H33: 675.11 | I33: 152 | J33: 151.92 | K33: 7.56 | P33: =SUM(C33:N33) -> 1692.57
A34: Bank Fees | P34: =SUM(C34:N34) -> 0
A35: Merchant fees | C35: 19.92 | D35: 54.95 | E35: 64.3 | F35: 251.9 | G35: 238.44 | H35: 397.25 | I35: 312.23 | J35: 327.52 | K35: 308.69 | L35: 289.41 | M35: 302.96 | N35: 157.96 | P35: =SUM(C35:N35) -> 2725.53
A36: Website | C36: 99 | D36: 99 | E36: 99 | F36: 99 | G36: 99 | H36: 99 | I36: 99 | J36: 99 | K36: 99 | L36: 99 | M36: 99 | N36: 99 | P36: =SUM(C36:N36) -> 1188
A37: Equipment(Stakes/Tarps) | E37: 243.83 | F37: 21.39 | G37: 813.25 | H37: 569.27 | I37: 74.89 | K37: 66.86 | L37: 570.74 | P37: =SUM(C37:N37) -> 2360.23
A38: Insurance - Liability | E38: 1223.6 | G38: 1010 | J38: 1010 | M38: 1010 | P38: =SUM(C38:N38) -> 4253.6
A39: Office Supplies | P39: =SUM(C39:N39) -> 0
A40: Gas | C40: 35.06 | D40: 102.47 | E40: 553.79 | F40: 595.32 | G40: 682.87 | H40: 776.27 | I40: 689.48 | J40: 274.47 | K40: 346.83 | L40: 463.32 | M40: 116.01 | P40: =SUM(C40:N40) -> 4635.89
A41: Canva (graphic design) | F41: 119.99 | P41: =SUM(C41:N41) -> 119.99
A42: Van Repair | F42: 123.64 | H42: 2000 | I42: 3258.73 | L42: 319.26 | M42: 209 | P42: =SUM(C42:N42) -> 5910.63
A43: Insurance - Workers Comp | P43: =SUM(C43:N43) -> 0
A44: Legal Zoom | N44: 529 | P44: =SUM(C44:N44) -> 529
A45: Regestration and Tag | G45: 64.89 | H45: 1.62 | P45: =SUM(C45:N45) -> 66.51
A46: GoDaddy | I46: 55.16 | M46: 22.17 | N46: 50.34 | P46: =SUM(C46:N46) -> 127.67
A47: Meeting
A48: Misc | P48: =SUM(C48:N48) -> 0
A49: Uniforms | P49: =SUM(C49:N49) -> 0
A50: Other Professional Fees | P50: =SUM(C50:N50) -> 0
A51: Outside Services | P51: =SUM(C51:N51) -> 0
A52: Postage | P52: =SUM(C52:N52) -> 0
A53: Mail Chimp | C53: 13 | D53: 13 | E53: 13 | F53: 13 | G53: 13 | H53: 13 | I53: 13 | J53: 13 | K53: 13 | L53: 13 | M53: 13 | N53: 13 | P53: =SUM(C53:N53) -> 156
A54: Rent - Equipment | P54: =SUM(C54:N54) -> 0
A55: Rent - Office | P55: =SUM(C55:N55) -> 0
A56: Rent - Storage | P56: =SUM(C56:N56) -> 0
A57: Vehicle Purchase | P57: =SUM(C57:N57) -> 0
A58: Taxes - Other | D58: 21.73 | F58: 330.29 | G58: 216.27 | I58: 1064.81 | J58: 462.62 | L58: 793.38 | M58: 483.74 | P58: =SUM(C58:N58) -> 3372.84
A59: Tires | G59: 133.96
A60: AT&T | C60: 96.83 | D60: 96.83 | E60: 96.71 | F60: 91.71 | G60: 101.7 | H60: 87.25 | I60: 142.48 | J60: 105.06 | K60: 105.06 | L60: 105.06 | M60: 105.09 | N60: 105.09 | P60: =SUM(C60:N60) -> 1238.87
A61: Travel | P61: =SUM(C61:N61) -> 0
A62: Utilities | P62: =SUM(C62:N62) -> 0
A63: Auto Insurance | C63: 206.2 | E63: 103.1 | F63: 103.1 | G63: 103.02 | I63: 305.45 | K63: 152.73 | L63: 305.46 | N63: 305.46 | P63: =SUM(C63:N63) -> 1584.52
A64: Repairs & Maintenance | D64: 198.61 | F64: 584.17 | G64: 72.18 | J64: 99.49 | L64: 202.92 | P64: =SUM(C64:N64) -> 1157.37
A65: Credit Card Payment | C65: 400 | D65: 400 | E65: 400 | F65: 400 | G65: 1589.08 | H65: 400 | I65: 400 | J65: 400 | K65: 1000 | L65: 1900 | N65: 400 | P65: =SUM(C65:N65) -> 7689.08
A66: ACCIDENTAL CHARGE | P66: =SUM(C66:N66) -> 0
A68: Penalties | N68: 10 | P68: =SUM(C68:N68) -> 10
A69: Interest Expense | P69: =SUM(C69:N69) -> 0
C71: =SUM(C14:C69) -> 1130.01 | D71: =SUM(D14:D69) -> 1166.59 | E71: =SUM(E14:E69) -> 6405.33 | F71: =SUM(F14:F69) -> 4246.74 | G71: =SUM(G14:G69) -> 8180.29 | H71: =SUM(H14:H69) -> 7921.77 | I71: =SUM(I14:I69) -> 9596.08 | J71: =SUM(J14:J69) -> 4546.08 | ... N71: =SUM(N14:N69) -> 1905.25
C72: =C11-C71 -> 5030.42 | D72: =C72+D11-D71 -> 4818.05 | E72: =D72+E11-E71 -> 3351.2 | F72: =E72+F11-F71 -> 3537.43 | G72: =F72+G11-G71 -> 4887.91 | H72: =G72+H11-H71 -> 2770.82 | I72: =H72+I11-I71 -> 2079.8 | J72: =I72+J11-J71 -> 3575.43 | K72: =J72+K11-K71 -> 6004.17 | ... N72: =M72+N11-N71 -> 320.63
A75: Mileage Driven
A76: enter actual miles | P76: =SUM(C76:N76) -> 0 | Q76: Total business mileage driven during the year.
H99: =SUM(H78:H98) -> 0

Sheet Credit Card
A3: Acct Name | C3: January | D3: February | E3: March | F3: April | G3: May | H3: June | I3: July | J3: August | K3: September | L3: October | M3: November | N3: December | P3: Total
P5: =SUM(C5:N5) -> 0
P6: =SUM(C6:N6) -> 0
A7: Credit Card Payments | C7: 400 | D7: 400 | E7: 400 | F7: 400 | G7: 1589.08 | P7: =SUM(C7:N7) -> 3189.08
A8: Cash Back rewards | P8: =SUM(C8:N8) -> 0
P9: =SUM(C9:N9) -> 0
P10: =SUM(C10:N10) -> 0
C11: =SUM(C5:C10) -> 400 | D11: =SUM(D5:D10) -> 400 | E11: =SUM(E5:E10) -> 400 | F11: =SUM(F5:F10) -> 400 | G11: =SUM(G5:G10) -> 1589.08 | H11: =SUM(H5:H10) -> 0 | I11: =SUM(I5:I10) -> 0 | J11: =SUM(J5:J10) -> 0 | ... N11: =SUM(N5:N10) -> 0
A12: Acct Name | C12: January | D12: February | E12: March | F12: April | G12: May | H12: June | I12: July | J12: August | K12: September | L12: October | M12: November | N12: December | P12: Total
A14: Distributions to owner | P14: =SUM(C14:N14) -> 0
P15: =SUM(C15:N15) -> 0
A17: Returns & Allowances | P17: =SUM(C17:N17) -> 0
A19: Contract Labor | P19: =SUM(C19:N19) -> 0
A20: Tires | P20: =SUM(C20:N20) -> 0
A21: Parts | P21: =SUM(C21:N21) -> 0
A22: Materials & Supplies | P22: =SUM(C22:N22) -> 0
P23: =SUM(C23:N23) -> 0
A24: Fixed Asset Purchase | P24: =SUM(C24:N24) -> 0 | Q24: enter add'l information for each purchase on separate tab
P25: =SUM(C25:N25) -> 0
A27: Accounting | P27: =SUM(C27:N27) -> 0
A28: Advertising | P28: =SUM(C28:N28) -> 0
A29: Bank Fees | P29: =SUM(C29:N29) -> 0
A30: Contributions | P30: =SUM(C30:N30) -> 0
A31: Dues & Subs | P31: =SUM(C31:N31) -> 0
A32: Education/Seminars | P32: =SUM(C32:N32) -> 0
A33: Gifts | P33: =SUM(C33:N33) -> 0
A34: Insurance - E&O | P34: =SUM(C34:N34) -> 0
A35: Insurance - Health | P35: =SUM(C35:N35) -> 0
A36: Insurance - Liability | P36: =SUM(C36:N36) -> 0
A37: Insurance - Property | P37: =SUM(C37:N37) -> 0
A38: Insurance - Workers Comp | P38: =SUM(C38:N38) -> 0
... A41: Meals & Entertainment | P41: =SUM(C41:N41) -> 0
A42: Trailer
A43: Misc | P43: =SUM(C43:N43) -> 0
A44: Office Supplies | P44: =SUM(C44:N44) -> 0
A45: Other Professional Fees | P45: =SUM(C45:N45) -> 0
A46: Outside Services | P46: =SUM(C46:N46) -> 0
A47: Postage | P47: =SUM(C47:N47) -> 0
A48: Printing & Reprod | P48: =SUM(C48:N48) -> 0
A49: Rent - Equipment | P49: =SUM(C49:N49) -> 0
A50: Rent - Office | P50: =SUM(C50:N50) -> 0
A51: Rent - Storage | P51: =SUM(C51:N51) -> 0
A52: Repairs & Maintenance | P52: =SUM(C52:N52) -> 0
A53: Taxes - Other | P53: =SUM(C53:N53) -> 0
A54: Telephone | P54: =SUM(C54:N54) -> 0
... A56: Utilities | P56: =SUM(C56:N56) -> 0
P57: =SUM(C57:N57) -> 0
P58: =SUM(C58:N58) -> 0
P59: =SUM(C59:N59) -> 0
P60: =SUM(C60:N60) -> 0
A62: Penalties | P62: =SUM(C62:N62) -> 0
A63: Interest Expense | P63: =SUM(C63:N63) -> 0
C65: =SUM(C14:C63) -> 0 | D65: =SUM(D14:D63) -> 0 | E65: =SUM(E14:E63) -> 0 | F65: =SUM(F14:F63) -> 0 | G65: =SUM(G14:G63) -> 0 | H65: =SUM(H14:H63) -> 0 | I65: =SUM(I14:I63) -> 0 | J65: =SUM(J14:J63) -> 0 | ... N65: =SUM(N14:N63) -> 0
C66: =C11-C65 -> 400 | D66: =C66+D11-D65 -> 800 | E66: =D66+E11-E65 -> 1200 | F66: =E66+F11-F65 -> 1600 | G66: =F66+G11-G65 -> 3189.08 | H66: =G66+H11-H65 -> 3189.08 | I66: =H66+I11-I65 -> 3189.08 | J66: =I66+J11-J65 -> 3189.08 | K66: =J66+K11-K65 -> 3189.08 | ... N66: =M66+N11-N65 -> 3189.08

Sheet Summary
A3: Acct Name | D3: Total
A5: Income | D5: ='Income & Expenses'!P5+'Credit Card'!P5 -> 56332.92
D6: ='Income & Expenses'!P6+'Credit Card'!P6 -> 0
A7: Credit Card Payments | D7: ='Income & Expenses'!P7+'Credit Card'!P7 -> 3189.08
D8: ='Income & Expenses'!P8+'Credit Card'!P8 -> 0
A9: Other source of funds: | D9: ='Income & Expenses'!P9+'Credit Card'!P9 -> 0
A10: Money from owner | D10: ='Income & Expenses'!P10+'Credit Card'!P10 -> 0
A12: Acct Name
A14: Distributions to owner | D14: ='Income & Expenses'!P14+'Credit Card'!P14 -> 0
A17: Returns & Allowances | D17: ='Income & Expenses'!P17+'Credit Card'!P17 -> 1175.99
A19: Contract Labor | D19: ='Income & Expenses'!P19+'Credit Card'!P19 -> 0
A20: Tires | D20: ='Income & Expenses'!P25+'Credit Card'!P20 -> 0
A21: Parts | D21: ='Income & Expenses'!P26+'Credit Card'!P21 -> 0
A22: Materials & Supplies | D22: ='Income & Expenses'!P27+'Credit Card'!P22 -> 0
A24: Fixed Asset Purchase | D24: ='Income & Expenses'!P29+'Credit Card'!P24 -> 4375.59
A27: Accounting | D27: ='Income & Expenses'!P32+'Credit Card'!P27 -> 0
A28: Advertising | D28: ='Income & Expenses'!P33+'Credit Card'!P28 -> 1692.57
A29: Bank Fees | D29: ='Income & Expenses'!P34+'Credit Card'!P29 -> 0
A30: Merchant fees | D30: ='Income & Expenses'!P35+'Credit Card'!P30 -> 2725.53
A31: Website | D31: ='Income & Expenses'!P36+'Credit Card'!P31 -> 1188
A32: Equipment(Stakes/Tarps) | D32: ='Income & Expenses'!P37+'Credit Card'!P32 -> 2360.23
A33: Insurance - Liability | D33: ='Income & Expenses'!P38+'Credit Card'!P33 -> 4253.6
A34: Office Supplies | D34: ='Income & Expenses'!P39+'Credit Card'!P34 -> 0
... A61: ACCIDENTAL CHARGE | D61: ='Income & Expenses'!P66+'Credit Card'!P61 -> 0
D62: ='Income & Expenses'!P68+'Credit Card'!P62 -> 10
A63: Penalties | D63: ='Income & Expenses'!P69+'Credit Card'!P63 -> 0
A64: Interest Expense | D64: ='Income & Expenses'!P69+'Credit Card'!P64 -> 0

Sheet Office in Home
A2: Acct Name | C2: January | D2: February | E2: March | F2: April | G2: May | H2: June | I2: July | J2: August | K2: September | L2: October | M2: November | N2: December | P2: Total
A3: Internet | P3: =SUM(C3:N3) -> 0 | Q3: take 75% and do not included in OIH figures
A4: Gas | P4: =SUM(C4:N4) -> 0
A5: Electric | P5: =SUM(C5:N5) -> 0
A6: Water | P6: =SUM(C6:N6) -> 0
A7: Sanitation | P7: =SUM(C7:N7) -> 0
A8: Security Monitoring | P8: =SUM(C8:N8) -> 0
A9: Pest Control | P9: =SUM(C9:N9) -> 0
A10: Lawn Care | P10: =SUM(C10:N10) -> 0
A11: Repairs/Maintenance | P11: =SUM(C11:N11) -> 0
A12: Rent
A14: Mortgage Interest Pd per Form 1098 | P14: =SUM(N14) -> 0
A15: Real Estate Taxes Paid - County | P15: =SUM(N15) -> 0
A16: Real Estate Taxes Paid - City | P16: =SUM(N16) -> 0
A17: Home Insurance | P17: =SUM(N17) -> 0
P19: =SUM(C19:N19) -> 0
A23: Office in home %
A24: Square footage of area used for office
A25: Total square footage of home
D27: =D24/D25 -> #DIV/0!
A29: Office In Home Deduction | D29: =P19*D27 -> #DIV/0!

Sheet Fixed Asset Purchase
A1: Fixed Asset Purchase
B4: Date of Purchase | D4: Description of item | F4: Amount Pd
B5: 45362 | D5: Rainbow Combo | F5: 2000

Sheet Personally Pd Expenses
A3: Acct Name | C3: January | D3: February | E3: March | F3: April | G3: May | H3: June | I3: July | J3: August | K3: September | L3: October | M3: November | N3: December | P3: Total
P5: =SUM(C5:N5) -> 0
P6: =SUM(C6:N6) -> 0
P7: =SUM(C7:N7) -> 0
P8: =SUM(C8:N8) -> 0
P9: =SUM(C9:N9) -> 0
P10: =SUM(C10:N10) -> 0
C11: =SUM(C5:C10) -> 0 | D11: =SUM(D5:D10) -> 0 | E11: =SUM(E5:E10) -> 0 | F11: =SUM(F5:F10) -> 0 | G11: =SUM(G5:G10) -> 0 | H11: =SUM(H5:H10) -> 0 | I11: =SUM(I5:I10) -> 0 | J11: =SUM(J5:J10) -> 0 | ... N11: =SUM(N5:N10) -> 0
A12: Acct Name | C12: January | D12: February | E12: March | F12: April | G12: May | H12: June | I12: July | J12: August | K12: September | L12: October | M12: November | N12: December | P12: Total
A14: Distributions to owner | P14: =SUM(C14:N14) -> 0
P15: =SUM(C15:N15) -> 0
A17: Returns & Allowances | P17: =SUM(C17:N17) -> 0
A19: Contract Labor | P19: =SUM(C19:N19) -> 0
A20: Tires
A21: Parts
A22: Materials & Supplies | P22: =SUM(C22:N22) -> 0
P23: =SUM(C23:N23) -> 0
A24: Fixed Asset Purchase | P24: =SUM(C24:N24) -> 0 | Q24: enter add'l information for each purchase on separate tab
P25: =SUM(C25:N25) -> 0
A27: Accounting | P27: =SUM(C27:N27) -> 0
A28: Advertising | P28: =SUM(C28:N28) -> 0
A29: Bank Fees | P29: =SUM(C29:N29) -> 0
A30: Contributions | P30: =SUM(C30:N30) -> 0
A31: Dues & Subs | P31: =SUM(C31:N31) -> 0
A32: Education/Seminars | P32: =SUM(C32:N32) -> 0
A33: Gifts | P33: =SUM(C33:N33) -> 0
A34: Insurance - E&O | P34: =SUM(C34:N34) -> 0
A35: Insurance - Health | P35: =SUM(C35:N35) -> 0
A36: Insurance - Liability | P36: =SUM(C36:N36) -> 0
A37: Insurance - Property | P37: =SUM(C37:N37) -> 0
A38: Insurance - Workers Comp | P38: =SUM(C38:N38) -> 0
... A41: Meals & Entertainment | P41: =SUM(C41:N41) -> 0
A42: Meeting
A43: Misc | P43: =SUM(C43:N43) -> 0
A44: Office Supplies | P44: =SUM(C44:N44) -> 0
A45: Other Professional Fees | P45: =SUM(C45:N45) -> 0
A46: Outside Services | P46: =SUM(C46:N46) -> 0
A47: Postage | P47: =SUM(C47:N47) -> 0
A48: Printing & Reprod | P48: =SUM(C48:N48) -> 0
A49: Rent - Equipment | P49: =SUM(C49:N49) -> 0
A50: Rent - Office | P50: =SUM(C50:N50) -> 0
A51: Rent - Storage | P51: =SUM(C51:N51) -> 0
A52: Repairs & Maintenance | P52: =SUM(C52:N52) -> 0
A53: Taxes - Other | P53: =SUM(C53:N53) -> 0
A54: Telephone | P54: =SUM(C54:N54) -> 0
... A56: Utilities | P56: =SUM(C56:N56) -> 0
P57: =SUM(C57:N57) -> 0
P58: =SUM(C58:N58) -> 0
A59: Credit Card Payment | P59: =SUM(C59:N59) -> 0
P60: =SUM(C60:N60) -> 0
A62: Penalties | P62: =SUM(C62:N62) -> 0
A63: Interest Expense | P63: =SUM(C63:N63) -> 0
C65: =SUM(C14:C63) -> 0 | D65: =SUM(D14:D63) -> 0 | E65: =SUM(E14:E63) -> 0 | F65: =SUM(F14:F63) -> 0 | G65: =SUM(G14:G63) -> 0 | H65: =SUM(H14:H63) -> 0 | I65: =SUM(I14:I63) -> 0 | J65: =SUM(J14:J63) -> 0 | ... N65: =SUM(N14:N63) -> 0
C66: =C11-C65 -> 0 | D66: =C66+D11-D65 -> 0 | E66: =D66+E11-E65 -> 0 | F66: =E66+F11-F65 -> 0 | G66: =F66+G11-G65 -> 0 | H66: =G66+H11-H65 -> 0 | I66: =H66+I11-I65 -> 0 | J66: =I66+J11-J65 -> 0 | K66: =J66+K11-K65 -> 0 | ... N66: =M66+N11-N65 -> 0
A69: Mileage Driven
A70: enter actual miles | P70: =SUM(C70:N70) -> 0 | Q70: Total business mileage driven during the year.
